osm_feature_extractor/__init__.py
osm_feature_extractor/data/base_data/countries.geojson
osm_feature_extractor/data/base_data/isle-of-wight.geojson
osm_feature_extractor/data/osm/isle-of-wight-latest.osm.pbf
osm_feature_extractor/feature_augmenting/STRATEGY.md
osm_feature_extractor/feature_augmenting/__init__.py
osm_feature_extractor/feature_augmenting/data_preparation.py
osm_feature_extractor/feature_augmenting/features_augmenter.py
osm_feature_extractor/feature_augmenting/features_to_tags.py
osm_feature_extractor/feature_extraction/osm_analyzer.py
osm_feature_extractor/feature_extraction/osm_datamodel.py
osm_feature_extractor/feature_extraction/osm_extractor.py
osm_feature_extractor/feature_extraction/osm_extractor_augmenter.py
osm_feature_extractor/feature_extraction/osm_extractor_batches.py
osm_feature_extractor/main.py
osm_feature_extractor/utils/config_parser.py
osm_feature_extractor/utils/img/data_frame.png
osm_feature_extractor/utils/img/data_kepler.png
osm_feature_extractor/utils/logger.py
osm_feature_extractor-0.3.0.dist-info/METADATA
osm_feature_extractor-0.3.0.dist-info/WHEEL
osm_feature_extractor-0.3.0.dist-info/entry_points.txt
osm_feature_extractor-0.3.0.dist-info/RECORD
