Metadata-Version: 2.1
Name: osm-feature-extractor
Version: 0.3.0
Summary: Library to extract OSM features and map them to GeoJSON polygons.
Home-page: https://github.com/diogomatoschaves/osm-feature-extractor
License: MIT
Keywords: osm,feature-augmentation,feature-extractor,osm-features
Author: Diogo Matos Chaves
Author-email: diogo_chaves@hotmail.com
Requires-Python: >=3.12,<4.0
Classifier: License :: OSI Approved :: MIT License
Classifier: Programming Language :: Python :: 3
Classifier: Programming Language :: Python :: 3.12
Requires-Dist: Rtree (>=1.3.0,<2.0.0)
Requires-Dist: geopandas (>=1.0.1,<2.0.0)
Requires-Dist: keplergl (==0.3.0)
Requires-Dist: matplotlib (>=3.9.2,<4.0.0)
Requires-Dist: numpy (>=2.0.1,<3.0.0)
Requires-Dist: ordered-set (>=4.1.0,<5.0.0)
Requires-Dist: osmium (>=3.7.0,<4.0.0)
Requires-Dist: pandas (>=2.2.2,<3.0.0)
Requires-Dist: pyturf (>=0.6.10,<0.7.0)
Requires-Dist: scipy (>=1.14.0,<2.0.0)
Requires-Dist: traittypes (>=0.2.1,<0.3.0)
Project-URL: Repository, https://github.com/diogomatoschaves/osm-feature-extractor
